hbreader/__init__.py
hbreader-0.9.0.dist-info/AUTHORS
hbreader-0.9.0.dist-info/LICENSE
hbreader-0.9.0.dist-info/METADATA
hbreader-0.9.0.dist-info/WHEEL
hbreader-0.9.0.dist-info/pbr.json
hbreader-0.9.0.dist-info/top_level.txt
hbreader-0.9.0.dist-info/RECORD
